rokit/__init__.py
rokit/__main__.py
rokit/__version__.py
rokit/cli.py
rokit/util.py
tests/__init__.py
tests/integration/__init__.py
tests/integration/test_cli.py
rokit-0.1.2.dist-info/LICENSE
rokit-0.1.2.dist-info/METADATA
rokit-0.1.2.dist-info/WHEEL
rokit-0.1.2.dist-info/entry_points.txt
rokit-0.1.2.dist-info/top_level.txt
rokit-0.1.2.dist-info/RECORD
