Metadata-Version: 2.1
Name: rokit
Version: 0.1.2
Summary: Redirection Optimization Kit
Home-page: https://github.com/wizardbyron/rokit
Author: wizardbyron
Author-email: wizardbyon@icloud.com
License: UNKNOWN
Keywords: url,redirection,redirect,verify,test,tests
Platform: UNKNOWN
Classifier: Development Status :: 1 - Planning
Classifier: License :: OSI Approved :: GNU General Public License v3 (GPLv3)
Classifier: Programming Language :: Python
Classifier: Programming Language :: Python :: 2.7
Classifier: Programming Language :: Python :: 3.6
Classifier: Programming Language :: Python :: 3.7
Classifier: Environment :: Console
Classifier: Intended Audience :: Developers
Classifier: Intended Audience :: System Administrators
Classifier: Topic :: Internet :: WWW/HTTP
Classifier: Topic :: Internet :: WWW/HTTP :: HTTP Servers
Classifier: Topic :: Internet :: WWW/HTTP :: Site Management
Classifier: Topic :: Internet :: WWW/HTTP :: Site Management :: Link Checking
Classifier: Topic :: Software Development :: Testing
Classifier: Topic :: Utilities
Requires-Python: >=2.6, >=3.6, <4
Requires-Dist: requests
Requires-Dist: click
Requires-Dist: future
